federated_monsters/federated_monsters.py
federated_monsters/client.py
federated_monsters/monster.py
federated_monsters/berkeley_db.py
federated_monsters/crypto.py
federated_monsters/global_vars.py
federated_monsters/box.py
federated_monsters/__init__.py
federated_monsters/db.py
federated_monsters-0.4.0.dist-info/metadata.json
federated_monsters-0.4.0.dist-info/DESCRIPTION.rst
federated_monsters-0.4.0.dist-info/top_level.txt
federated_monsters-0.4.0.dist-info/METADATA
federated_monsters-0.4.0.dist-info/RECORD
federated_monsters-0.4.0.dist-info/WHEEL
