Metadata-Version: 2.0
Name: federated-monsters
Version: 0.4.0
Summary: Federated Monsters is a game that seeks to follow the format of games like Pokemon, but to instead use a federated server format to store and trade creatures
Home-page: https://github.com/colatkinson/federated_monsters
Author: Colin Atkinson
Author-email: 114d71d1@opayq.com
License: BSD
Keywords: federated_monsters
Platform: UNKNOWN
Classifier: Development Status :: 2 - Pre-Alpha
Classifier: Intended Audience :: Developers
Classifier: License :: OSI Approved :: BSD License
Classifier: Natural Language :: English
Classifier: Programming Language :: Python :: 2
Classifier: Programming Language :: Python :: 2.6
Classifier: Programming Language :: Python :: 2.7
Classifier: Programming Language :: Python :: 3
Classifier: Programming Language :: Python :: 3.3
Classifier: Programming Language :: Python :: 3.4
Requires-Dist: bsddb3 (>=5.2.0)
Requires-Dist: pycrypto (>=2.5)
